Workbook

Sheet Leyenda
A1: RedVital — Tareas del Sprint 3
A2: Entrega | B2: Semana 10 — Review Sprint 3 y Planning Sprint 4 (alrededor del 13–14 de octubre de 2026)
A3: Fuente | B3: Backlog del Sprint 3 v1.2, con la historia de Identidad dividida en dos: HU-304 (inicio de sesión y claves públicas, 3 pts) y HU-330 (renovación, término, token de servicio y auditoría, 2 pts).
A5: Cómo usar
A6: Filtrar | B6: En la hoja Tareas, usa las flechas del encabezado: Responsable, Frente, Tipo, Entregable S10, Ruta crítica, Nivel o Estado.
A7: Celdas para editar | B7: Las de fondo amarillo claro: Estado (lista desplegable), Fecha inicio y Fecha fin en la hoja Tareas; y los dos supuestos en azul de la hoja Carga por persona.
A8: Formato de fecha | B8: dd/mm/aaaa, por ejemplo 05/10/2026. Si la fecha fin queda antes que la de inicio, se marca en rojo.
A9: Estados | B9: Pendiente · En curso (amarillo) · Bloqueada (rojo) · Hecha (verde). Las hojas Historias y Carga por persona recalculan el avance a partir del Estado.
A11: Columnas
A12: Depende de | B12: Tareas que deben estar terminadas para poder cerrar esta. Las tareas de pruebas se pueden empezar a escribir antes, contra el contrato publicado en T-301.5.
A13: Bloquea a | B13: Tareas que esperan a esta. Se generó a partir de «Depende de»; si cambias una dependencia, actualiza también esta columna.
A14: Nivel | B14: Longitud de la cadena de dependencias más larga que llega a la tarea. Nivel 0 = no depende de nada y puede empezar el primer día. Una tarea no puede empezar antes que todas sus dependencias, que siempre tienen un nivel menor. Sirve para ordenar al cuadrar fechas.
A15: Ruta crítica | B15: Sí cuando la historia está en una de las dos cadenas más largas: Contratos → Donación → Motor → Tamizaje → Inventario → QA → Informe → TD V1 → Presentación, y Contratos → Identidad → Gateway → QA.
A16: Tipo | B16: Código · Base de datos · Pruebas · Infraestructura · Diagrama · Documento · Gestión.
A17: Pts | B17: Los puntos viven en la hoja Historias; las tareas no se estiman.
A19: Tareas para agendar primero
A20: T-303.1 | B20: Llave de prueba: desbloquea a Damián y a Tomás sin esperar a Identidad.
A21: T-304.1, T-306.1, T-312.1 | B21: Esquemas de las tres bases: los necesita el generador de datos sintéticos (T-302.2).
A22: T-301.1 a T-301.5 | B22: Contratos: casi todo el código y las pruebas dependen de ellos.
A23: T-322.3 | B23: Resolver RDS-13 (ciclo de vencimiento): bloquea el proceso de vencimiento (T-311.1).
A24: T-314.1 | B24: Confirmar la máquina de QA y su acceso externo (riesgo RT-02).
A25: T-323.1 | B25: Diagrama de infraestructura nuevo: lo necesitan Infraestructura V2 y el despliegue C4.
A26: T-318.1 y T-319.1 | B26: ADR-017 y ADR-018: su aprobación en Mesa desbloquea la terminología de todos los documentos.
A27: T-328.5 | B27: Cargar historias y tareas en GitHub Projects.

Sheet Tareas
A1: ID tarea | B1: Historia | C1: Título de la historia | D1: Frente | E1: Tarea | F1: Responsable | G1: Rol | H1: Tipo | I1: Componente | J1: Entregable S10 | K1: MoSCoW | L1: Ruta crítica | M1: Depende de | N1: Bloquea a | O1: Nivel | P1: Estado | Q1: Fecha inicio | R1: Fecha fin | S1: Nota
A2: T-301.1 | B2: HU-301 | C2: Contratos OpenAPI del incremento publicados antes del código | D2: Contratos y datos de prueba | E2: Extraer del DD V2.0 las operaciones del incremento con sus errores y degradaciones | F2: Sara | G2: Arquitecta | H2: Documento | I2: Identidad, Donación, Campañas | J2: Incremento de valor | K2: Must | L2: Sí | M2: — | N2: T-301.2, T-301.3, T-301.4, T-302.1 | O2: 0 | P2: Pendiente
A3: T-301.2 | B3: HU-301 | C3: Contratos OpenAPI del incremento publicados antes del código | D3: Contratos y datos de prueba | E3: Escribir el OpenAPI de Identidad: sesión, renovación, término y claves públicas | F3: Sara | G3: Arquitecta | H3: Código | I3: Identidad, Donación, Campañas | J3: Incremento de valor | K3: Must | L3: Sí | M3: T-301.1 | N3: T-301.5, T-304.2 | O3: 1 | P3: Pendiente
A4: T-301.3 | B4: HU-301 | C4: Contratos OpenAPI del incremento publicados antes del código | D4: Contratos y datos de prueba | E4: Escribir el OpenAPI de Donación: búsqueda de donante, donación, tamizaje, existencias, despacho, disposición y eventos | F4: Sara | G4: Arquitecta | H4: Código | I4: Identidad, Donación, Campañas | J4: Incremento de valor | K4: Must | L4: Sí | M4: T-301.1 | N4: T-301.5, T-306.2 | O4: 1 | P4: Pendiente
A5: T-301.4 | B5: HU-301 | C5: Contratos OpenAPI del incremento publicados antes del código | D5: Contratos y datos de prueba | E5: Escribir el OpenAPI de Campañas: consulta, detalle, publicación y cierre | F5: Sara | G5: Arquitecta | H5: Código | I5: Identidad, Donación, Campañas | J5: Incremento de valor | K5: Must | L5: Sí | M5: T-301.1 | N5: T-301.5, T-306.4, T-312.2 | O5: 1 | P5: Pendiente
A6: T-301.5 | B6: HU-301 | C6: Contratos OpenAPI del incremento publicados antes del código | D6: Contratos y datos de prueba | E6: Publicar los contratos en redvital-docs, enlazarlos desde cada repositorio y avisar a QA | F6: Sara | G6: Arquitecta | H6: Documento | I6: Identidad, Donación, Campañas | J6: Incremento de valor | K6: Must | L6: Sí | M6: T-301.2, T-301.3, T-301.4 | N6: T-305.1, T-313.3, T-315.3 | O6: 2 | P6: Pendiente | S6: Desde aquí QA puede escribir pruebas contra el contrato
A7: T-302.1 | B7: HU-302 | C7: Datos sintéticos coherentes para las tres bases | D7: Contratos y datos de prueba | E7: Definir el conjunto sintético: bancos, U3 y U4, donantes, campañas por estado y unidades por estado, incluidas vencidas y próximas a vencer | F7: Tomás | G7: QA / Tester | H7: Base de datos | I7: Bases de datos | J7: Incremento de valor | K7: Must | L7: No | M7: T-301.1 | N7: T-302.2, T-325.2 | O7: 1 | P7: Pendiente
A8: T-302.2 | B8: HU-302 | C8: Datos sintéticos coherentes para las tres bases | D8: Contratos y datos de prueba | E8: Construir el generador versionado con una sola semilla para db_identidad, db_donacion y db_campana | F8: Tomás | G8: QA / Tester | H8: Base de datos | I8: Bases de datos | J8: Incremento de valor | K8: Must | L8: No | M8: T-302.1, T-304.1, T-306.1, T-312.1 | N8: T-302.3, T-311.3 | O8: 2 | P8: Pendiente | S8: Necesita los esquemas de las tres bases
A9: T-302.3 | B9: HU-302 | C9: Datos sintéticos coherentes para las tres bases | D9: Contratos y datos de prueba | E9: Integrar la carga de datos en los trabajos de migración de cada base | F9: Tomás | G9: QA / Tester | H9: Base de datos | I9: Bases de datos | J9: Incremento de valor | K9: Must | L9: No | M9: T-302.2 | N9: T-302.4, T-314.3 | O9: 3 | P9: Pendiente
A10: T-302.4 | B10: HU-302 | C10: Datos sintéticos coherentes para las tres bases | D10: Contratos y datos de prueba | E10: Verificar identificadores coherentes entre bases y ausencia de causa clínica | F10: Tomás | G10: QA / Tester | H10: Pruebas | I10: Bases de datos | J10: Incremento de valor | K10: Must | L10: No | M10: T-302.3 | N10: — | O10: 4 | P10: Pendiente
A11: T-303.1 | B11: HU-303 | C11: Llave de prueba para firmar tokens en desarrollo y pruebas | D11: Contratos y datos de prueba | E11: Generar el par de llaves de prueba y la utilidad que emite tokens U3, U4 y de servicio con las reivindicaciones de ADR-008 | F11: Sebastián | G11: Desarrollador (.NET) | H11: Código | I11: Identidad | J11: Incremento de valor | K11: Must | L11: No | M11: — | N11: T-303.2 | O11: 0 | P11: Pendiente | S11: Desbloquea a Damián y a Tomás sin esperar a Identidad
A12: T-303.2 | B12: HU-303 | C12: Llave de prueba para firmar tokens en desarrollo y pruebas | D12: Contratos y datos de prueba | E12: Cargar la llave solo en el perfil de desarrollo y en la suite; documentar su uso | F12: Sebastián | G12: Desarrollador (.NET) | H12: Código | I12: Identidad | J12: Incremento de valor | K12: Must | L12: No | M12: T-303.1 | N12: T-303.3, T-306.7, T-312.6, T-325.2 | O12: 1 | P12: Pendiente
A13: T-303.3 | B13: HU-303 | C13: Llave de prueba para firmar tokens en desarrollo y pruebas | D13: Contratos y datos de prueba | E13: Prueba que confirma que la configuración de QA rechaza tokens de la llave de prueba | F13: Sebastián | G13: Desarrollador (.NET) | H13: Pruebas | I13: Identidad | J13: Incremento de valor | K13: Must | L13: No | M13: T-303.2, T-305.2 | N13: T-315.5 | O13: 6 | P13: Pendiente
A14: T-304.1 | B14: HU-304 | C14: Identidad: inicio de sesión y claves públicas | D14: Identidad | E14: Base db_identidad: esquema del incremento, migraciones EF Core y roles de propietario y de servicio | F14: Sebastián | G14: Desarrollador (.NET) | H14: Base de datos | I14: Servicio de Identidad + db_identidad | J14: Incremento de valor | K14: Must | L14: Sí | M14: — | N14: T-302.2, T-304.2, T-330.4 | O14: 0 | P14: Pendiente
A15: T-304.2 | B15: HU-304 | C15: Identidad: inicio de sesión y claves públicas | D15: Identidad | E15: Inicio de sesión: verificación de credenciales con respuesta que no distingue usuario de contraseña | F15: Sebastián | G15: Desarrollador (.NET) | H15: Código | I15: Servicio de Identidad + db_identidad | J15: Incremento de valor | K15: Must | L15: Sí | M15: T-304.1, T-301.2 | N15: T-304.3 | O15: 2 | P15: Pendiente
A16: T-304.3 | B16: HU-304 | C16: Identidad: inicio de sesión y claves públicas | D16: Identidad | E16: Emisión de token RS256 de 15 minutos con institución y ruta territorial, sin dato personal | F16: Sebastián | G16: Desarrollador (.NET) | H16: Código | I16: Servicio de Identidad + db_identidad | J16: Incremento de valor | K16: Must | L16: Sí | M16: T-304.2 | N16: T-304.4, T-330.1, T-330.3 | O16: 3 | P16: Pendiente
A17: T-304.4 | B17: HU-304 | C17: Identidad: inicio de sesión y claves públicas | D17: Identidad | E17: Endpoint de claves públicas (JWKS) | F17: Sebastián | G17: Desarrollador (.NET) | H17: Código | I17: Servicio de Identidad + db_identidad | J17: Incremento de valor | K17: Must | L17: Sí | M17: T-304.3 | N17: T-304.5, T-305.2 | O17: 4 | P17: Pendiente | S17: Primera entrega de Identidad: con esto el gateway ya valida tokens reales
A18: T-304.5 | B18: HU-304 | C18: Identidad: inicio de sesión y claves públicas | D18: Identidad | E18: Pruebas unitarias y de integración de sesión y claves públicas | F18: Sebastián | G18: Desarrollador (.NET) | H18: Pruebas | I18: Servicio de Identidad + db_identidad | J18: Incremento de valor | K18: Must | L18: Sí | M18: T-304.4 | N18: T-314.6 | O18: 5 | P18: Pendiente
A19: T-330.1 | B19: HU-330 | C19: Identidad: renovación, término, token de servicio y auditoría | D19: Identidad | E19: Renovación con sesión de 8 horas y rotación de la credencial de renovación | F19: Sebastián | G19: Desarrollador (.NET) | H19: Código | I19: Servicio de Identidad + db_identidad | J19: Incremento de valor | K19: Must | L19: No | M19: T-304.3 | N19: T-330.2 | O19: 4 | P19: Pendiente
A20: T-330.2 | B20: HU-330 | C20: Identidad: renovación, término, token de servicio y auditoría | D20: Identidad | E20: Término de sesión que invalida la renovación | F20: Sebastián | G20: Desarrollador (.NET) | H20: Código | I20: Servicio de Identidad + db_identidad | J20: Incremento de valor | K20: Must | L20: No | M20: T-330.1 | N20: T-330.5 | O20: 5 | P20: Pendiente
A21: T-330.3 | B21: HU-330 | C21: Identidad: renovación, término, token de servicio y auditoría | D21: Identidad | E21: Emisión del token de servicio de Donación | F21: Sebastián | G21: Desarrollador (.NET) | H21: Código | I21: Servicio de Identidad + db_identidad | J21: Incremento de valor | K21: Must | L21: No | M21: T-304.3 | N21: T-330.5 | O21: 4 | P21: Pendiente
A22: T-330.4 | B22: HU-330 | C22: Identidad: renovación, término, token de servicio y auditoría | D22: Identidad | E22: Serie de auditoría de Identidad y operación interna para registrar las denegaciones del gateway | F22: Sebastián | G22: Desarrollador (.NET) | H22: Base de datos | I22: Servicio de Identidad + db_identidad | J22: Incremento de valor | K22: Must | L22: No | M22: T-304.1 | N22: T-305.4, T-315.8, T-330.5 | O22: 1 | P22: Pendiente | S22: Solo anexado por permisos del rol
A23: T-330.5 | B23: HU-330 | C23: Identidad: renovación, término, token de servicio y auditoría | D23: Identidad | E23: Pruebas de renovación, término, token de servicio y auditoría | F23: Sebastián | G23: Desarrollador (.NET) | H23: Pruebas | I23: Servicio de Identidad + db_identidad | J23: Incremento de valor | K23: Must | L23: No | M23: T-330.2, T-330.3, T-330.4 | N23: T-314.6, T-315.5 | O23: 6 | P23: Pendiente
A24: T-305.1 | B24: HU-305 | C24: Gateway: enrutamiento, validación del token y compuerta por rol | D24: API Gateway | E24: Rutas YARP /v1/* hacia Identidad, Donación y Campañas; excluir /internal/ y el puerto de gestión | F24: Sebastián | G24: Desarrollador (.NET) | H24: Código | I24: API Gateway (YARP) | J24: Incremento de valor | K24: Must | L24: Sí | M24: T-301.5 | N24: T-305.2, T-305.5 | O24: 3 | P24: Pendiente
A25: T-305.2 | B25: HU-305 | C25: Gateway: enrutamiento, validación del token y compuerta por rol | D25: API Gateway | E25: Validación de firma y vigencia del token contra el JWKS de Identidad | F25: Sebastián | G25: Desarrollador (.NET) | H25: Código | I25: API Gateway (YARP) | J25: Incremento de valor | K25: Must | L25: Sí | M25: T-305.1, T-304.4 | N25: T-303.3, T-305.3, T-317.1 | O25: 5 | P25: Pendiente
A26: T-305.3 | B26: HU-305 | C26: Gateway: enrutamiento, validación del token y compuerta por rol | D26: API Gateway | E26: Compuerta por ruta y rol según la matriz del DD para las rutas del incremento | F26: Sebastián | G26: Desarrollador (.NET) | H26: Código | I26: API Gateway (YARP) | J26: Incremento de valor | K26: Must | L26: Sí | M26: T-305.2 | N26: T-305.4, T-305.6 | O26: 6 | P26: Pendiente
A27: T-305.4 | B27: HU-305 | C27: Gateway: enrutamiento, validación del token y compuerta por rol | D27: API Gateway | E27: Envío de las denegaciones a la serie de auditoría de Identidad | F27: Sebastián | G27: Desarrollador (.NET) | H27: Código | I27: API Gateway (YARP) | J27: Incremento de valor | K27: Must | L27: Sí | M27: T-305.3, T-330.4 | N27: T-305.6 | O27: 7 | P27: Pendiente
A28: T-305.5 | B28: HU-305 | C28: Gateway: enrutamiento, validación del token y compuerta por rol | D28: API Gateway | E28: Generación y propagación del identificador de correlación | F28: Sebastián | G28: Desarrollador (.NET) | H28: Código | I28: API Gateway (YARP) | J28: Incremento de valor | K28: Must | L28: Sí | M28: T-305.1 | N28: T-305.6 | O28: 4 | P28: Pendiente
A29: T-305.6 | B29: HU-305 | C29: Gateway: enrutamiento, validación del token y compuerta por rol | D29: API Gateway | E29: Pruebas del gateway | F29: Sebastián | G29: Desarrollador (.NET) | H29: Pruebas | I29: API Gateway (YARP) | J29: Incremento de valor | K29: Must | L29: Sí | M29: T-305.3, T-305.4, T-305.5 | N29: T-314.6, T-315.4 | O29: 8 | P29: Pendiente
A30: T-306.1 | B30: HU-306 | C30: Donación: registro de donación asociada a campaña, con degradación | D30: Donación | E30: Base db_donacion: esquema del incremento con Flyway, roles y tablas de solo anexado sin UPDATE ni DELETE para el rol de servicio | F30: Damián | G30: Desarrollador (Java) | H30: Base de datos | I30: Servicio de Donación + db_donacion | J30: Incremento de valor | K30: Must | L30: Sí | M30: — | N30: T-302.2, T-306.2, T-307.1 | O30: 0 | P30: Pendiente
A31: T-306.2 | B31: HU-306 | C31: Donación: registro de donación asociada a campaña, con degradación | D31: Donación | E31: Búsqueda de donante sobre el conjunto sintético | F31: Damián | G31: Desarrollador (Java) | H31: Código | I31: Servicio de Donación + db_donacion | J31: Incremento de valor | K31: Must | L31: Sí | M31: T-306.1, T-301.3 | N31: T-306.3 | O31: 2 | P31: Pendiente
A32: T-306.3 | B32: HU-306 | C32: Donación: registro de donación asociada a campaña, con degradación | D32: Donación | E32: Registro de donación que genera la unidad resultante y su evento | F32: Damián | G32: Desarrollador (Java) | H32: Código | I32: Servicio de Donación + db_donacion | J32: Incremento de valor | K32: Must | L32: Sí | M32: T-306.2 | N32: T-306.4, T-306.5, T-306.6, T-307.4 | O32: 3 | P32: Pendiente
A33: T-306.4 | B33: HU-306 | C33: Donación: registro de donación asociada a campaña, con degradación | D33: Donación | E33: Adaptador hacia Campañas con plazo de 3 s y resultado tipado; degradación con campania_id nulo declarada | F33: Damián | G33: Desarrollador (Java) | H33: Código | I33: Servicio de Donación + db_donacion | J33: Incremento de valor | K33: Must | L33: Sí | M33: T-306.3, T-301.4 | N33: T-306.7 | O33: 4 | P33: Pendiente | S33: Se prueba con un Campañas simulado hasta que exista T-312.3
A34: T-306.5 | B34: HU-306 | C34: Donación: registro de donación asociada a campaña, con degradación | D34: Donación | E34: Idempotencia del registro de donación (DS-10) | F34: Damián | G34: Desarrollador (Java) | H34: Código | I34: Servicio de Donación + db_donacion | J34: Incremento de valor | K34: Must | L34: Sí | M34: T-306.3 | N34: T-306.7 | O34: 4 | P34: Pendiente
A35: T-306.6 | B35: HU-306 | C35: Donación: registro de donación asociada a campaña, con degradación | D35: Donación | E35: Identificador de correlación en los registros de aplicación | F35: Damián | G35: Desarrollador (Java) | H35: Código | I35: Servicio de Donación + db_donacion | J35: Incremento de valor | K35: Must | L35: Sí | M35: T-306.3 | N35: T-306.7 | O35: 4 | P35: Pendiente
A36: T-306.7 | B36: HU-306 | C36: Donación: registro de donación asociada a campaña, con degradación | D36: Donación | E36: Pruebas del servicio con tokens de la llave de prueba | F36: Damián | G36: Desarrollador (Java) | H36: Pruebas | I36: Servicio de Donación + db_donacion | J36: Incremento de valor | K36: Must | L36: Sí | M36: T-303.2, T-306.4, T-306.5, T-306.6 | N36: T-314.6, T-315.4 | O36: 5 | P36: Pendiente
A37: T-307.1 | B37: HU-307 | C37: Donación: motor de transiciones con el catálogo completo | D37: Donación | E37: Catálogo transicion_valida con las 13 transiciones del DD, cargado por migración | F37: Damián | G37: Desarrollador (Java) | H37: Base de datos | I37: Servicio de Donación + db_donacion | J37: Incremento de valor | K37: Must | L37: Sí | M37: T-306.1 | N37: T-307.2 | O37: 1 | P37: Pendiente
A38: T-307.2 | B38: HU-307 | C38: Donación: motor de transiciones con el catálogo completo | D38: Donación | E38: Motor único que lee el catálogo, rechaza lo no listado sin cambiar estado y registra el intento | F38: Damián | G38: Desarrollador (Java) | H38: Código | I38: Servicio de Donación + db_donacion | J38: Incremento de valor | K38: Must | L38: Sí | M38: T-307.1 | N38: T-307.3, T-307.4, T-308.1, T-309.1, T-310.2, T-311.1 | O38: 2 | P38: Pendiente
A39: T-307.3 | B39: HU-307 | C39: Donación: motor de transiciones con el catálogo completo | D39: Donación | E39: Invocación aislada del motor, sin base de datos, para recorrer los 82 casos | F39: Damián | G39: Desarrollador (Java) | H39: Código | I39: Servicio de Donación + db_donacion | J39: Incremento de valor | K39: Must | L39: Sí | M39: T-307.2 | N39: T-315.2 | O39: 3 | P39: Pendiente | S39: Habilita EC-36
A40: T-307.4 | B40: HU-307 | C40: Donación: motor de transiciones con el catálogo completo | D40: Donación | E40: Hacer pasar el alta de la unidad de T-306.3 por el motor | F40: Damián | G40: Desarrollador (Java) | H40: Código | I40: Servicio de Donación + db_donacion | J40: Incremento de valor | K40: Must | L40: Sí | M40: T-307.2, T-306.3 | N40: — | O40: 4 | P40: Pendiente
A41: T-308.1 | B41: HU-308 | C41: Donación: ingreso a tamizaje y veredicto apto / no apto | D41: Donación | E41: Operación de ingreso a tamizaje a través del motor | F41: Damián | G41: Desarrollador (Java) | H41: Código | I41: Servicio de Donación | J41: Incremento de valor | K41: Must | L41: Sí | M41: T-307.2 | N41: T-308.2 | O41: 3 | P41: Pendiente
A42: T-308.2 | B42: HU-308 | C42: Donación: ingreso a tamizaje y veredicto apto / no apto | D42: Donación | E42: Veredicto apto / no apto con catálogo observacion_operativa y sin causa clínica | F42: Damián | G42: Desarrollador (Java) | H42: Código | I42: Servicio de Donación | J42: Incremento de valor | K42: Must | L42: Sí | M42: T-308.1 | N42: T-308.3 | O42: 4 | P42: Pendiente
A43: T-308.3 | B43: HU-308 | C43: Donación: ingreso a tamizaje y veredicto apto / no apto | D43: Donación | E43: Pruebas de tamizaje | F43: Damián | G43: Desarrollador (Java) | H43: Pruebas | I43: Servicio de Donación | J43: Incremento de valor | K43: Must | L43: Sí | M43: T-308.2 | N43: T-314.6, T-315.4 | O43: 5 | P43: Pendiente
A44: T-309.1 | B44: HU-309 | C44: Donación: consulta de existencias filtrada por institución | D44: Donación | E44: Consulta única de unidades disponibles (DS-04): aptas, no vencidas, sin estado indeterminado | F44: Damián | G44: Desarrollador (Java) | H44: Código | I44: Servicio de Donación | J44: Incremento de valor | K44: Must | L44: Sí | M44: T-307.2 | N44: T-309.2, T-310.1 | O44: 3 | P44: Pendiente | S44: La usan inventario y despacho
A45: T-309.2 | B45: HU-309 | C45: Donación: consulta de existencias filtrada por institución | D45: Donación | E45: Existencias por componente y tipo de sangre filtradas por la institución del token | F45: Damián | G45: Desarrollador (Java) | H45: Código | I45: Servicio de Donación | J45: Incremento de valor | K45: Must | L45: Sí | M45: T-309.1 | N45: T-309.3, T-317.2 | O45: 4 | P45: Pendiente
A46: T-309.3 | B46: HU-309 | C46: Donación: consulta de existencias filtrada por institución | D46: Donación | E46: Respuesta indistinguible ante institución ajena y registro del intento en la bitácora | F46: Damián | G46: Desarrollador (Java) | H46: Código | I46: Servicio de Donación | J46: Incremento de valor | K46: Must | L46: Sí | M46: T-309.2 | N46: T-309.4 | O46: 5 | P46: Pendiente | S46: EC-01
A47: T-309.4 | B47: HU-309 | C47: Donación: consulta de existencias filtrada por institución | D47: Donación | E47: Pruebas de existencias | F47: Damián | G47: Desarrollador (Java) | H47: Pruebas | I47: Servicio de Donación | J47: Incremento de valor | K47: Must | L47: Sí | M47: T-309.3 | N47: T-314.6, T-315.4 | O47: 6 | P47: Pendiente
A48: T-310.1 | B48: HU-310 | C48: Donación: despacho y disposición final con confirmación | D48: Donación | E48: Despacho a través del motor, solo por la institución custodia (IN-21) y solo sobre unidades disponibles | F48: Damián | G48: Desarrollador (Java) | H48: Código | I48: Servicio de Donación | J48: Incremento de valor | K48: Must | L48: No | M48: T-309.1 | N48: T-310.3 | O48: 4 | P48: Pendiente | S48: EC-12, EC-39
A49: T-310.2 | B49: HU-310 | C49: Donación: despacho y disposición final con confirmación | D49: Donación | E49: Disposición final con campo confirmacion; 422 sin cambio de estado si no coincide | F49: Damián | G49: Desarrollador (Java) | H49: Código | I49: Servicio de Donación | J49: Incremento de valor | K49: Must | L49: No | M49: T-307.2 | N49: T-310.3 | O49: 3 | P49: Pendiente | S49: EC-19, parte de API
A50: T-310.3 | B50: HU-310 | C50: Donación: despacho y disposición final con confirmación | D50: Donación | E50: Registro de despacho y desecho en la serie de auditoría de Donación | F50: Damián | G50: Desarrollador (Java) | H50: Base de datos | I50: Servicio de Donación | J50: Incremento de valor | K50: Must | L50: No | M50: T-310.1, T-310.2 | N50: T-310.4, T-315.8 | O50: 5 | P50: Pendiente | S50: EC-05
A51: T-310.4 | B51: HU-310 | C51: Donación: despacho y disposición final con confirmación | D51: Donación | E51: Pruebas de despacho y disposición final | F51: Damián | G51: Desarrollador (Java) | H51: Pruebas | I51: Servicio de Donación | J51: Incremento de valor | K51: Must | L51: No | M51: T-310.3 | N51: T-314.6, T-315.4, T-315.7 | O51: 6 | P51: Pendiente
A52: T-311.1 | B52: HU-311 | C52: Donación: exclusión automática de unidades vencidas | D52: Donación | E52: Proceso programado que vence unidades a través del motor, con bloqueo consultivo (DS-06) y contenedor en UTC | F52: Damián | G52: Desarrollador (Java) | H52: Código | I52: Servicio de Donación | J52: Incremento de valor | K52: Must | L52: No | M52: T-307.2, T-322.3 | N52: T-311.2 | O52: 3 | P52: Pendiente | S52: Necesita resuelta la contradicción del ciclo de vencimiento (RDS-13)
A53: T-311.2 | B53: HU-311 | C53: Donación: exclusión automática de unidades vencidas | D53: Donación | E53: Actor sistema con el nombre del proceso y correlación por ciclo | F53: Damián | G53: Desarrollador (Java) | H53: Código | I53: Servicio de Donación | J53: Incremento de valor | K53: Must | L53: No | M53: T-311.1 | N53: T-311.3 | O53: 4 | P53: Pendiente | S53: EC-33
A54: T-311.3 | B54: HU-311 | C54: Donación: exclusión automática de unidades vencidas | D54: Donación | E54: Pruebas con unidades sembradas como vencidas | F54: Damián | G54: Desarrollador (Java) | H54: Pruebas | I54: Servicio de Donación | J54: Incremento de valor | K54: Must | L54: No | M54: T-311.2, T-302.2 | N54: T-314.6, T-315.8 | O54: 5 | P54: Pendiente | S54: EC-13
A55: T-312.1 | B55: HU-312 | C55: Campañas: consultar, publicar y cerrar campañas | D55: Campañas | E55: Base db_campana: esquema del incremento, migraciones EF Core y roles | F55: Sebastián | G55: Desarrollador (.NET) | H55: Base de datos | I55: Servicio de Campañas + db_campana | J55: Incremento de valor | K55: Must | L55: No | M55: — | N55: T-302.2, T-312.2 | O55: 0 | P55: Pendiente
A56: T-312.2 | B56: HU-312 | C56: Campañas: consultar, publicar y cerrar campañas | D56: Campañas | E56: Consulta de campañas con filtrado por rol y jurisdicción | F56: Sebastián | G56: Desarrollador (.NET) | H56: Código | I56: Servicio de Campañas + db_campana | J56: Incremento de valor | K56: Must | L56: No | M56: T-312.1, T-301.4 | N56: T-312.3, T-312.4 | O56: 2 | P56: Pendiente
A57: T-312.3 | B57: HU-312 | C57: Campañas: consultar, publicar y cerrar campañas | D57: Campañas | E57: Detalle de campaña para usuario y para el token de servicio de Donación | F57: Sebastián | G57: Desarrollador (.NET) | H57: Código | I57: Servicio de Campañas + db_campana | J57: Incremento de valor | K57: Must | L57: No | M57: T-312.2 | N57: T-312.6 | O57: 3 | P57: Pendiente | S57: Lo consume T-306.4
A58: T-312.4 | B58: HU-312 | C58: Campañas: consultar, publicar y cerrar campañas | D58: Campañas | E58: Publicación y cierre solo para U4 de la institución organizadora | F58: Sebastián | G58: Desarrollador (.NET) | H58: Código | I58: Servicio de Campañas + db_campana | J58: Incremento de valor | K58: Must | L58: No | M58: T-312.2 | N58: T-312.5 | O58: 3 | P58: Pendiente
A59: T-312.5 | B59: HU-312 | C59: Campañas: consultar, publicar y cerrar campañas | D59: Campañas | E59: Serie de auditoría registro_auditoria_camp para publicación y cierre | F59: Sebastián | G59: Desarrollador (.NET) | H59: Base de datos | I59: Servicio de Campañas + db_campana | J59: Incremento de valor | K59: Must | L59: No | M59: T-312.4 | N59: T-312.6 | O59: 4 | P59: Pendiente
A60: T-312.6 | B60: HU-312 | C60: Campañas: consultar, publicar y cerrar campañas | D60: Campañas | E60: Pruebas del servicio con tokens de la llave de prueba | F60: Sebastián | G60: Desarrollador (.NET) | H60: Pruebas | I60: Servicio de Campañas + db_campana | J60: Incremento de valor | K60: Must | L60: No | M60: T-303.2, T-312.3, T-312.5 | N60: T-314.6, T-315.4 | O60: 5 | P60: Pendiente
A61: T-313.1 | B61: HU-313 | C61: Integración continua de los repositorios del incremento | D61: Integración y despliegue | E61: Flujo de GitHub Actions por repositorio (Identidad, Gateway, Donación, Campañas, Web): construcción y pruebas | F61: Veli | G61: DevOps | H61: Infraestructura | I61: Infraestructura | J61: Despliegue en QA | K61: Must | L61: No | M61: — | N61: T-313.2, T-313.3, T-313.4, T-315.1 | O61: 0 | P61: Pendiente
A62: T-313.2 | B62: HU-313 | C62: Integración continua de los repositorios del incremento | D62: Integración y despliegue | E62: Gitleaks y Grype en cada flujo | F62: Veli | G62: DevOps | H62: Infraestructura | I62: Infraestructura | J62: Despliegue en QA | K62: Must | L62: No | M62: T-313.1 | N62: — | O62: 1 | P62: Pendiente
A63: T-313.3 | B63: HU-313 | C63: Integración continua de los repositorios del incremento | D63: Integración y despliegue | E63: Verificación del contrato OpenAPI en cada PR | F63: Veli | G63: DevOps | H63: Infraestructura | I63: Infraestructura | J63: Despliegue en QA | K63: Must | L63: No | M63: T-313.1, T-301.5 | N63: — | O63: 3 | P63: Pendiente | S63: EC-22
A64: T-313.4 | B64: HU-313 | C64: Integración continua de los repositorios del incremento | D64: Integración y despliegue | E64: Publicación de imágenes al fusionar en develop | F64: Veli | G64: DevOps | H64: Infraestructura | I64: Infraestructura | J64: Despliegue en QA | K64: Must | L64: No | M64: T-313.1 | N64: T-314.2 | O64: 1 | P64: Pendiente
A65: T-313.5 | B65: HU-313 | C65: Integración continua de los repositorios del incremento | D65: Integración y despliegue | E65: Protección de las ramas main y develop según GitFlow | F65: Veli | G65: DevOps | H65: Infraestructura | I65: Infraestructura | J65: Despliegue en QA | K65: Must | L65: No | M65: — | N65: — | O65: 0 | P65: Pendiente
A66: T-314.1 | B66: HU-314 | C66: Despliegue del incremento en QA con un solo comando | D66: Integración y despliegue | E66: Confirmar especificaciones reales de la máquina de QA y su acceso desde fuera de la red | F66: Veli | G66: DevOps | H66: Infraestructura | I66: Infraestructura | J66: Despliegue en QA | K66: Must | L66: Sí | M66: — | N66: T-314.2, T-323.3 | O66: 0 | P66: Pendiente | S66: Riesgo RT-02
A67: T-314.2 | B67: HU-314 | C67: Despliegue del incremento en QA con un solo comando | D67: Integración y despliegue | E67: Compose de QA: borde, web, gateway, tres servicios, tres bases y tres trabajos de migración, en el orden de ADR-014-E1 | F67: Veli | G67: DevOps | H67: Infraestructura | I67: Infraestructura | J67: Despliegue en QA | K67: Must | L67: Sí | M67: T-313.4, T-314.1 | N67: T-314.3, T-314.4 | O67: 2 | P67: Pendiente
A68: T-314.3 | B68: HU-314 | C68: Despliegue del incremento en QA con un solo comando | D68: Integración y despliegue | E68: Verificaciones de salud y medición del arranque en 10 minutos o menos | F68: Veli | G68: DevOps | H68: Infraestructura | I68: Infraestructura | J68: Despliegue en QA | K68: Must | L68: Sí | M68: T-314.2, T-302.3 | N68: T-314.5, T-314.6 | O68: 4 | P68: Pendiente | S68: EC-23
A69: T-314.4 | B69: HU-314 | C69: Despliegue del incremento en QA con un solo comando | D69: Integración y despliegue | E69: Detener y levantar un contenedor sin reiniciar el resto | F69: Veli | G69: DevOps | H69: Infraestructura | I69: Infraestructura | J69: Despliegue en QA | K69: Must | L69: Sí | M69: T-314.2 | N69: T-315.6 | O69: 3 | P69: Pendiente | S69: Necesario para EC-08
A70: T-314.5 | B70: HU-314 | C70: Despliegue del incremento en QA con un solo comando | D70: Integración y despliegue | E70: Medir memoria y CPU de cada contenedor | F70: Veli | G70: DevOps | H70: Infraestructura | I70: Infraestructura | J70: Despliegue en QA | K70: Must | L70: Sí | M70: T-314.3 | N70: T-323.3 | O70: 5 | P70: Pendiente | S70: T-411
A71: T-314.6 | B71: HU-314 | C71: Despliegue del incremento en QA con un solo comando | D71: Integración y despliegue | E71: Desplegar el incremento completo en QA | F71: Veli | G71: DevOps | H71: Infraestructura | I71: Infraestructura | J71: Despliegue en QA | K71: Must | L71: Sí | M71: T-314.3, T-304.5, T-330.5, T-305.6, T-306.7, T-308.3, T-309.4, T-310.4, T-311.3, T-312.6 | N71: T-316.1, T-320.6, T-322.4, T-323.4, T-329.1 | O71: 9 | P71: Pendiente | S71: Hito: sin esto no hay informe de pruebas
A72: T-315.1 | B72: HU-315 | C72: Pruebas automatizadas del flujo, la degradación y los escenarios | D72: Pruebas | E72: Estructura de la suite y su ejecución en la CI | F72: Tomás | G72: QA / Tester | H72: Pruebas | I72: Varios | J72: Informe de pruebas | K72: Must | L72: No | M72: T-313.1 | N72: T-315.2, T-315.3 | O72: 1 | P72: Pendiente
A73: T-315.2 | B73: HU-315 | C73: Pruebas automatizadas del flujo, la degradación y los escenarios | D73: Pruebas | E73: Suite de los 82 casos del motor: 13 aceptadas, 68 rechazadas y el alta, en menos de 2 minutos | F73: Tomás | G73: QA / Tester | H73: Pruebas | I73: Varios | J73: Informe de pruebas | K73: Must | L73: No | M73: T-307.3, T-315.1 | N73: T-316.1 | O73: 4 | P73: Pendiente | S73: EC-36, EC-04
A74: T-315.3 | B74: HU-315 | C74: Pruebas automatizadas del flujo, la degradación y los escenarios | D74: Pruebas | E74: Validación de las respuestas contra los contratos OpenAPI | F74: Tomás | G74: QA / Tester | H74: Pruebas | I74: Varios | J74: Informe de pruebas | K74: Must | L74: No | M74: T-301.5, T-315.1 | N74: T-316.1 | O74: 3 | P74: Pendiente
A75: T-315.4 | B75: HU-315 | C75: Pruebas automatizadas del flujo, la degradación y los escenarios | D75: Pruebas | E75: Punta a punta por el gateway: sesión → donación con campaña → tamizaje → inventario → despacho | F75: Tomás | G75: QA / Tester | H75: Pruebas | I75: Varios | J75: Informe de pruebas | K75: Must | L75: No | M75: T-305.6, T-306.7, T-308.3, T-309.4, T-310.4, T-312.6 | N75: T-315.5, T-315.6, T-325.4 | O75: 9 | P75: Pendiente | S75: Se escribe contra el contrato desde T-301.5
A76: T-315.5 | B76: HU-315 | C76: Pruebas automatizadas del flujo, la degradación y los escenarios | D76: Pruebas | E76: Seguridad: EC-01 con U3 y U4, EC-02 en respuestas y registros, EC-03 incluida la llave de prueba rechazada | F76: Tomás | G76: QA / Tester | H76: Pruebas | I76: Varios | J76: Informe de pruebas | K76: Must | L76: No | M76: T-315.4, T-330.5, T-303.3 | N76: T-316.1 | O76: 10 | P76: Pendiente
A77: T-315.6 | B77: HU-315 | C77: Pruebas automatizadas del flujo, la degradación y los escenarios | D77: Pruebas | E77: Resiliencia e integridad: EC-08 con Campañas detenido y EC-10 con cien reenvíos | F77: Tomás | G77: QA / Tester | H77: Pruebas | I77: Varios | J77: Informe de pruebas | K77: Must | L77: No | M77: T-315.4, T-314.4 | N77: T-316.1 | O77: 10 | P77: Pendiente
A78: T-315.7 | B78: HU-315 | C78: Pruebas automatizadas del flujo, la degradación y los escenarios | D78: Pruebas | E78: Bloqueos: EC-12, EC-19 por API y EC-39 | F78: Tomás | G78: QA / Tester | H78: Pruebas | I78: Varios | J78: Informe de pruebas | K78: Must | L78: No | M78: T-310.4 | N78: T-316.1 | O78: 7 | P78: Pendiente
A79: T-315.8 | B79: HU-315 | C79: Pruebas automatizadas del flujo, la degradación y los escenarios | D79: Pruebas | E79: Acciones automáticas y auditoría: EC-13, EC-33 y EC-05 (rol sin UPDATE ni DELETE) | F79: Tomás | G79: QA / Tester | H79: Pruebas | I79: Varios | J79: Informe de pruebas | K79: Must | L79: No | M79: T-311.3, T-330.4, T-310.3 | N79: T-316.1 | O79: 6 | P79: Pendiente
A80: T-316.1 | B80: HU-316 | C80: Ejecución de pruebas en QA e informe de pruebas | D80: Pruebas | E80: Ejecutar la suite completa sobre QA | F80: Tomás | G80: QA / Tester | H80: Pruebas | I80: Documentación | J80: Informe de pruebas | K80: Must | L80: Sí | M80: T-314.6, T-315.2, T-315.3, T-315.5, T-315.6, T-315.7, T-315.8 | N80: T-316.2, T-316.3, T-324.4, T-325.5, T-327.1, T-329.3 | O80: 11 | P80: Pendiente | S80: Hito
A81: T-316.2 | B81: HU-316 | C81: Ejecución de pruebas en QA e informe de pruebas | D81: Pruebas | E81: Registrar los defectos como Issues con clase «Defecto» | F81: Tomás | G81: QA / Tester | H81: Pruebas | I81: Documentación | J81: Informe de pruebas | K81: Must | L81: Sí | M81: T-316.1 | N81: T-316.3 | O81: 12 | P81: Pendiente
A82: T-316.3 | B82: HU-316 | C82: Ejecución de pruebas en QA e informe de pruebas | D82: Pruebas | E82: Redactar el informe de pruebas: casos, resultados, evidencia y defectos abiertos | F82: Tomás | G82: QA / Tester | H82: Documento | I82: Documentación | J82: Informe de pruebas | K82: Must | L82: Sí | M82: T-316.1, T-316.2 | N82: T-321.2, T-325.6, T-329.4 | O82: 13 | P82: Pendiente | S82: Entregable de la Semana 10
A83: T-317.1 | B83: HU-317 | C83: Web: pantallas de sesión e inventario conectadas al gateway | D83: Web | E83: Pantallas de inicio y cierre de sesión conectadas por el gateway | F83: Carlos | G83: Scrum Master / PM | H83: Código | I83: Aplicación Web | J83: Incremento de valor | K83: Should | L83: No | M83: T-305.2 | N83: T-317.2 | O83: 6 | P83: Pendiente
A84: T-317.2 | B84: HU-317 | C84: Web: pantallas de sesión e inventario conectadas al gateway | D84: Web | E84: Pantalla de existencias consumiendo el contrato real | F84: Carlos | G84: Scrum Master / PM | H84: Código | I84: Aplicación Web | J84: Incremento de valor | K84: Should | L84: No | M84: T-309.2, T-317.1 | N84: T-317.3 | O84: 7 | P84: Pendiente
A85: T-317.3 | B85: HU-317 | C85: Web: pantallas de sesión e inventario conectadas al gateway | D85: Web | E85: Estados de carga, error y reintento en cada llamada | F85: Carlos | G85: Scrum Master / PM | H85: Código | I85: Aplicación Web | J85: Incremento de valor | K85: Should | L85: No | M85: T-317.2 | N85: T-317.4 | O85: 8 | P85: Pendiente | S85: RA-07
A86: T-317.4 | B86: HU-317 | C86: Web: pantallas de sesión e inventario conectadas al gateway | D86: Web | E86: Revisión: sin lógica de negocio y datos visiblemente sintéticos | F86: Carlos | G86: Scrum Master / PM | H86: Pruebas | I86: Aplicación Web | J86: Incremento de valor | K86: Should | L86: No | M86: T-317.3 | N86: — | O86: 9 | P86: Pendiente
A87: T-318.1 | B87: HU-318 | C87: ADR-017: arquitectura definida como microservicios | D87: Arquitectura | E87: Redactar ADR-017 con la plantilla de Herramientas V3.0 | F87: Sara | G87: Arquitecta | H87: Documento | I87: Documentación | J87: Actualización de arquitectura | K87: Must | L87: No | M87: — | N87: T-318.2 | O87: 0 | P87: Pendiente
A88: T-318.2 | B88: HU-318 | C88: ADR-017: arquitectura definida como microservicios | D88: Arquitectura | E88: Declarar la granularidad final y la lista de documentos y entradas del radar afectados | F88: Sara | G88: Arquitecta | H88: Documento | I88: Documentación | J88: Actualización de arquitectura | K88: Must | L88: No | M88: T-318.1 | N88: T-318.3, T-328.4 | O88: 1 | P88: Pendiente
A89: T-318.3 | B89: HU-318 | C89: ADR-017: arquitectura definida como microservicios | D89: Arquitectura | E89: Aprobar en Mesa de Arquitectura y marcar ADR-003 y ADR-014 como reemplazados o enmendados | F89: Sara | G89: Arquitecta | H89: Documento | I89: Documentación | J89: Actualización de arquitectura | K89: Must | L89: No | M89: T-318.2, T-328.4 | N89: T-320.1, T-321.1, T-322.2, T-323.2, T-324.3, T-326.1 | O89: 3 | P89: Pendiente | S89: Desbloquea la terminología de todos los documentos
A90: T-319.1 | B90: HU-319 | C90: ADR-018: evaluación de Kafka | D90: Arquitectura | E90: Clasificar las aristas de ADR-014 y comparar HTTP con bandeja, RabbitMQ y Kafka por benchmarking | F90: Sara | G90: Arquitecta | H90: Documento | I90: Documentación | J90: Actualización de arquitectura | K90: Must | L90: No | M90: — | N90: T-319.2 | O90: 0 | P90: Pendiente
A91: T-319.2 | B91: HU-319 | C91: ADR-018: evaluación de Kafka | D91: Arquitectura | E91: Redactar ADR-018 con costos, decisión y disparador | F91: Sara | G91: Arquitecta | H91: Documento | I91: Documentación | J91: Actualización de arquitectura | K91: Must | L91: No | M91: T-319.1 | N91: T-319.3, T-328.4 | O91: 1 | P91: Pendiente
A92: T-319.3 | B92: HU-319 | C92: ADR-018: evaluación de Kafka | D92: Arquitectura | E92: Aprobar ADR-018 en Mesa de Arquitectura | F92: Sara | G92: Arquitecta | H92: Documento | I92: Documentación | J92: Actualización de arquitectura | K92: Must | L92: No | M92: T-319.2, T-328.4 | N92: T-321.1, T-326.2 | O92: 3 | P92: Pendiente
A93: T-320.1 | B93: HU-320 | C93: Modelo C4 conforme a c4model.com y SDD V2 | D93: Arquitectura | E93: Rehacer C4 nivel 1 (contexto) con la notación de c4model.com | F93: Sara | G93: Arquitecta | H93: Diagrama | I93: Documentación | J93: SDD V2 | K93: Must | L93: No | M93: T-318.3 | N93: T-320.2 | O93: 4 | P93: Pendiente
A94: T-320.2 | B94: HU-320 | C94: Modelo C4 conforme a c4model.com y SDD V2 | D94: Arquitectura | E94: Rehacer C4 nivel 2 (contenedores) con cada microservicio agrupado con su base | F94: Sara | G94: Arquitecta | H94: Diagrama | I94: Documentación | J94: SDD V2 | K94: Must | L94: No | M94: T-320.1 | N94: T-320.3, T-320.4, T-320.7 | O94: 5 | P94: Pendiente
A95: T-320.3 | B95: HU-320 | C95: Modelo C4 conforme a c4model.com y SDD V2 | D95: Arquitectura | E95: C4 nivel 3 (componentes) de los microservicios que faltaban | F95: Sara | G95: Arquitecta | H95: Diagrama | I95: Documentación | J95: SDD V2 | K95: Must | L95: No | M95: T-320.2 | N95: T-320.5 | O95: 6 | P95: Pendiente
A96: T-320.4 | B96: HU-320 | C96: Modelo C4 conforme a c4model.com y SDD V2 | D96: Arquitectura | E96: Diagrama de despliegue C4 alineado con el diagrama de infraestructura nuevo | F96: Sara | G96: Arquitecta | H96: Diagrama | I96: Documentación | J96: SDD V2 | K96: Must | L96: No | M96: T-320.2, T-323.1 | N96: T-320.5, T-323.4 | O96: 6 | P96: Pendiente
A97: T-320.5 | B97: HU-320 | C97: Modelo C4 conforme a c4model.com y SDD V2 | D97: Arquitectura | E97: Gemelos Mermaid C4 en redvital-docs | F97: Sara | G97: Arquitecta | H97: Diagrama | I97: Documentación | J97: SDD V2 | K97: Must | L97: No | M97: T-320.3, T-320.4 | N97: T-320.6 | O97: 7 | P97: Pendiente | S97: RD-04
A98: T-320.6 | B98: HU-320 | C98: Modelo C4 conforme a c4model.com y SDD V2 | D98: Arquitectura | E98: Emitir SDD V2: resultados de la PoC, ajustes del primer flujo, RDS-03, RDS-06, C4 y terminología | F98: Sara | G98: Arquitecta | H98: Documento | I98: Documentación | J98: SDD V2 | K98: Must | L98: No | M98: T-320.5, T-314.6 | N98: T-329.4 | O98: 10 | P98: Pendiente | S98: Entregable de la Semana 10
A99: T-320.7 | B99: HU-320 | C99: Modelo C4 conforme a c4model.com y SDD V2 | D99: Arquitectura | E99: Entregar los diagramas C4 a Alex para la vista general del DD V3 | F99: Sara | G99: Arquitecta | H99: Diagrama | I99: Documentación | J99: SDD V2 | K99: Must | L99: No | M99: T-320.2 | N99: T-322.1 | O99: 6 | P99: Pendiente
A100: T-321.1 | B100: HU-321 | C100: SAD V3 | D100: Documentación | E100: SAD V3: terminología de microservicios y registro de ADR-017 y ADR-018 | F100: Sara | G100: Arquitecta | H100: Documento | I100: Documentación | J100: SAD V3 | K100: Must | L100: No | M100: T-318.3, T-319.3 | N100: T-321.2 | O100: 4 | P100: Pendiente
...

Sheet Historias
A1: Historia | B1: Título | C1: Frente | D1: Responsable | E1: MoSCoW | F1: Pts | G1: Componente | H1: Entregable S10 | I1: Origen | J1: Ruta crítica | K1: Tareas | L1: Tareas hechas | M1: Avance
A2: HU-301 | B2: Contratos OpenAPI del incremento publicados antes del código | C2: Contratos y datos de prueba | D2: Sara | E2: Must | F2: 2 | G2: Identidad, Donación, Campañas | H2: Incremento de valor | I2: DD V2.0, EC-22 | J2: Sí | K2: =COUNTIF(Tareas!$B$2:$B$135,A2) -> 5 | L2: =COUNTIFS(Tareas!$B$2:$B$135,A2,Tareas!$P$2:$P$135,"Hecha") -> 0 | M2: =IF(K2=0,0,L2/K2) -> 0
A3: HU-302 | B3: Datos sintéticos coherentes para las tres bases | C3: Contratos y datos de prueba | D3: Tomás | E3: Must | F3: 3 | G3: Bases de datos | H3: Incremento de valor | I3: DD V2.0, EC-23 | J3: No | K3: =COUNTIF(Tareas!$B$2:$B$135,A3) -> 4 | L3: =COUNTIFS(Tareas!$B$2:$B$135,A3,Tareas!$P$2:$P$135,"Hecha") -> 0 | M3: =IF(K3=0,0,L3/K3) -> 0
A4: HU-303 | B4: Llave de prueba para firmar tokens en desarrollo y pruebas | C4: Contratos y datos de prueba | D4: Sebastián | E4: Must | F4: 1 | G4: Identidad | H4: Incremento de valor | I4: ADR-008 | J4: No | K4: =COUNTIF(Tareas!$B$2:$B$135,A4) -> 3 | L4: =COUNTIFS(Tareas!$B$2:$B$135,A4,Tareas!$P$2:$P$135,"Hecha") -> 0 | M4: =IF(K4=0,0,L4/K4) -> 0
A5: HU-304 | B5: Identidad: inicio de sesión y claves públicas | C5: Identidad | D5: Sebastián | E5: Must | F5: 3 | G5: Servicio de Identidad + db_identidad | H5: Incremento de valor | I5: RF-23, ADR-008, EC-03 | J5: Sí | K5: =COUNTIF(Tareas!$B$2:$B$135,A5) -> 5 | L5: =COUNTIFS(Tareas!$B$2:$B$135,A5,Tareas!$P$2:$P$135,"Hecha") -> 0 | M5: =IF(K5=0,0,L5/K5) -> 0
A6: HU-330 | B6: Identidad: renovación, término, token de servicio y auditoría | C6: Identidad | D6: Sebastián | E6: Must | F6: 2 | G6: Servicio de Identidad + db_identidad | H6: Incremento de valor | I6: RF-24, ADR-008, ADR-016, EC-03 | J6: No | K6: =COUNTIF(Tareas!$B$2:$B$135,A6) -> 5 | L6: =COUNTIFS(Tareas!$B$2:$B$135,A6,Tareas!$P$2:$P$135,"Hecha") -> 0 | M6: =IF(K6=0,0,L6/K6) -> 0
A7: HU-305 | B7: Gateway: enrutamiento, validación del token y compuerta por rol | C7: API Gateway | D7: Sebastián | E7: Must | F7: 3 | G7: API Gateway (YARP) | H7: Incremento de valor | I7: ADR-007, ADR-011, RNF-02 | J7: Sí | K7: =COUNTIF(Tareas!$B$2:$B$135,A7) -> 6 | L7: =COUNTIFS(Tareas!$B$2:$B$135,A7,Tareas!$P$2:$P$135,"Hecha") -> 0 | M7: =IF(K7=0,0,L7/K7) -> 0
A8: HU-306 | B8: Donación: registro de donación asociada a campaña, con degradación | C8: Donación | D8: Damián | E8: Must | F8: 5 | G8: Servicio de Donación + db_donacion | H8: Incremento de valor | I8: RF-03, RF-04, EC-08, EC-10 | J8: Sí | K8: =COUNTIF(Tareas!$B$2:$B$135,A8) -> 7 | L8: =COUNTIFS(Tareas!$B$2:$B$135,A8,Tareas!$P$2:$P$135,"Hecha") -> 0 | M8: =IF(K8=0,0,L8/K8) -> 0
A9: HU-307 | B9: Donación: motor de transiciones con el catálogo completo | C9: Donación | D9: Damián | E9: Must | F9: 3 | G9: Servicio de Donación + db_donacion | H9: Incremento de valor | I9: DS-03, EC-04, EC-36 | J9: Sí | K9: =COUNTIF(Tareas!$B$2:$B$135,A9) -> 4 | L9: =COUNTIFS(Tareas!$B$2:$B$135,A9,Tareas!$P$2:$P$135,"Hecha") -> 0 | M9: =IF(K9=0,0,L9/K9) -> 0
A10: HU-308 | B10: Donación: ingreso a tamizaje y veredicto apto / no apto | C10: Donación | D10: Damián | E10: Must | F10: 2 | G10: Servicio de Donación | H10: Incremento de valor | I10: RF-05, RNF-01, EC-02 | J10: Sí | K10: =COUNTIF(Tareas!$B$2:$B$135,A10) -> 3 | L10: =COUNTIFS(Tareas!$B$2:$B$135,A10,Tareas!$P$2:$P$135,"Hecha") -> 0 | M10: =IF(K10=0,0,L10/K10) -> 0
A11: HU-309 | B11: Donación: consulta de existencias filtrada por institución | C11: Donación | D11: Damián | E11: Must | F11: 2 | G11: Servicio de Donación | H11: Incremento de valor | I11: RF-07, RNF-02, EC-01 | J11: Sí | K11: =COUNTIF(Tareas!$B$2:$B$135,A11) -> 4 | L11: =COUNTIFS(Tareas!$B$2:$B$135,A11,Tareas!$P$2:$P$135,"Hecha") -> 0 | M11: =IF(K11=0,0,L11/K11) -> 0
A12: HU-310 | B12: Donación: despacho y disposición final con confirmación | C12: Donación | D12: Damián | E12: Must | F12: 3 | G12: Servicio de Donación | H12: Incremento de valor | I12: RF-06, EC-12, EC-19, EC-39 | J12: No | K12: =COUNTIF(Tareas!$B$2:$B$135,A12) -> 4 | L12: =COUNTIFS(Tareas!$B$2:$B$135,A12,Tareas!$P$2:$P$135,"Hecha") -> 0 | M12: =IF(K12=0,0,L12/K12) -> 0
A13: HU-311 | B13: Donación: exclusión automática de unidades vencidas | C13: Donación | D13: Damián | E13: Must | F13: 3 | G13: Servicio de Donación | H13: Incremento de valor | I13: RF-18, EC-13, EC-33 | J13: No | K13: =COUNTIF(Tareas!$B$2:$B$135,A13) -> 3 | L13: =COUNTIFS(Tareas!$B$2:$B$135,A13,Tareas!$P$2:$P$135,"Hecha") -> 0 | M13: =IF(K13=0,0,L13/K13) -> 0
... A31: HU-329 | B31: Presentación de la Semana 10 y entrega en buzón | C31: Gestión | D31: Carlos | E31: Must | F31: 2 | G31: Documentación | H31: Presentación | I31: Cronograma S10 | J31: Sí | K31: =COUNTIF(Tareas!$B$2:$B$135,A31) -> 4 | L31: =COUNTIFS(Tareas!$B$2:$B$135,A31,Tareas!$P$2:$P$135,"Hecha") -> 0 | M31: =IF(K31=0,0,L31/K31) -> 0
A32: Total | F32: =SUM(F2:F31) -> 86 | K32: =SUM(K2:K31) -> 134 | L32: =SUM(L2:L31) -> 0 | M32: =IF(K32=0,0,L32/K32) -> 0

Sheet Carga por persona
A1: Persona | B1: Rol | C1: Historias | D1: Pts | E1: Horas equivalentes | F1: Tareas | G1: Pendientes | H1: En curso | I1: Bloqueadas | J1: Hechas | K1: Avance
A2: Damián | B2: Desarrollador (Java) | C2: =COUNTIF(Historias!$D$2:$D$31,A2) -> 6 | D2: =SUMIF(Historias!$D$2:$D$31,A2,Historias!$F$2:$F$31) -> 18 | E2: =D2*$B$13 -> 36 | F2: =COUNTIF(Tareas!$F$2:$F$135,A2) -> 25 | G2: =COUNTIFS(Tareas!$F$2:$F$135,A2,Tareas!$P$2:$P$135,"Pendiente") -> 25 | H2: =COUNTIFS(Tareas!$F$2:$F$135,A2,Tareas!$P$2:$P$135,"En curso") -> 0 | I2: =COUNTIFS(Tareas!$F$2:$F$135,A2,Tareas!$P$2:$P$135,"Bloqueada") -> 0 | J2: =COUNTIFS(Tareas!$F$2:$F$135,A2,Tareas!$P$2:$P$135,"Hecha") -> 0 | K2: =IF(F2=0,0,J2/F2) -> 0
A3: Tomás | B3: QA / Tester | C3: =COUNTIF(Historias!$D$2:$D$31,A3) -> 4 | D3: =SUMIF(Historias!$D$2:$D$31,A3,Historias!$F$2:$F$31) -> 18 | E3: =D3*$B$13 -> 36 | F3: =COUNTIF(Tareas!$F$2:$F$135,A3) -> 21 | G3: =COUNTIFS(Tareas!$F$2:$F$135,A3,Tareas!$P$2:$P$135,"Pendiente") -> 21 | H3: =COUNTIFS(Tareas!$F$2:$F$135,A3,Tareas!$P$2:$P$135,"En curso") -> 0 | I3: =COUNTIFS(Tareas!$F$2:$F$135,A3,Tareas!$P$2:$P$135,"Bloqueada") -> 0 | J3: =COUNTIFS(Tareas!$F$2:$F$135,A3,Tareas!$P$2:$P$135,"Hecha") -> 0 | K3: =IF(F3=0,0,J3/F3) -> 0
A4: Sebastián | B4: Desarrollador (.NET) | C4: =COUNTIF(Historias!$D$2:$D$31,A4) -> 5 | D4: =SUMIF(Historias!$D$2:$D$31,A4,Historias!$F$2:$F$31) -> 14 | E4: =D4*$B$13 -> 28 | F4: =COUNTIF(Tareas!$F$2:$F$135,A4) -> 25 | G4: =COUNTIFS(Tareas!$F$2:$F$135,A4,Tareas!$P$2:$P$135,"Pendiente") -> 25 | H4: =COUNTIFS(Tareas!$F$2:$F$135,A4,Tareas!$P$2:$P$135,"En curso") -> 0 | I4: =COUNTIFS(Tareas!$F$2:$F$135,A4,Tareas!$P$2:$P$135,"Bloqueada") -> 0 | J4: =COUNTIFS(Tareas!$F$2:$F$135,A4,Tareas!$P$2:$P$135,"Hecha") -> 0 | K4: =IF(F4=0,0,J4/F4) -> 0
A5: Sara | B5: Arquitecta | C5: =COUNTIF(Historias!$D$2:$D$31,A5) -> 5 | D5: =SUMIF(Historias!$D$2:$D$31,A5,Historias!$F$2:$F$31) -> 12 | E5: =D5*$B$13 -> 24 | F5: =COUNTIF(Tareas!$F$2:$F$135,A5) -> 20 | G5: =COUNTIFS(Tareas!$F$2:$F$135,A5,Tareas!$P$2:$P$135,"Pendiente") -> 20 | H5: =COUNTIFS(Tareas!$F$2:$F$135,A5,Tareas!$P$2:$P$135,"En curso") -> 0 | I5: =COUNTIFS(Tareas!$F$2:$F$135,A5,Tareas!$P$2:$P$135,"Bloqueada") -> 0 | J5: =COUNTIFS(Tareas!$F$2:$F$135,A5,Tareas!$P$2:$P$135,"Hecha") -> 0 | K5: =IF(F5=0,0,J5/F5) -> 0
A6: Veli | B6: DevOps | C6: =COUNTIF(Historias!$D$2:$D$31,A6) -> 3 | D6: =SUMIF(Historias!$D$2:$D$31,A6,Historias!$F$2:$F$31) -> 8 | E6: =D6*$B$13 -> 16 | F6: =COUNTIF(Tareas!$F$2:$F$135,A6) -> 15 | G6: =COUNTIFS(Tareas!$F$2:$F$135,A6,Tareas!$P$2:$P$135,"Pendiente") -> 15 | H6: =COUNTIFS(Tareas!$F$2:$F$135,A6,Tareas!$P$2:$P$135,"En curso") -> 0 | I6: =COUNTIFS(Tareas!$F$2:$F$135,A6,Tareas!$P$2:$P$135,"Bloqueada") -> 0 | J6: =COUNTIFS(Tareas!$F$2:$F$135,A6,Tareas!$P$2:$P$135,"Hecha") -> 0 | K6: =IF(F6=0,0,J6/F6) -> 0
A7: Alex | B7: Product Owner | C7: =COUNTIF(Historias!$D$2:$D$31,A7) -> 3 | D7: =SUMIF(Historias!$D$2:$D$31,A7,Historias!$F$2:$F$31) -> 8 | E7: =D7*$B$13 -> 16 | F7: =COUNTIF(Tareas!$F$2:$F$135,A7) -> 13 | G7: =COUNTIFS(Tareas!$F$2:$F$135,A7,Tareas!$P$2:$P$135,"Pendiente") -> 13 | H7: =COUNTIFS(Tareas!$F$2:$F$135,A7,Tareas!$P$2:$P$135,"En curso") -> 0 | I7: =COUNTIFS(Tareas!$F$2:$F$135,A7,Tareas!$P$2:$P$135,"Bloqueada") -> 0 | J7: =COUNTIFS(Tareas!$F$2:$F$135,A7,Tareas!$P$2:$P$135,"Hecha") -> 0 | K7: =IF(F7=0,0,J7/F7) -> 0
A8: Carlos | B8: Scrum Master / PM | C8: =COUNTIF(Historias!$D$2:$D$31,A8) -> 4 | D8: =SUMIF(Historias!$D$2:$D$31,A8,Historias!$F$2:$F$31) -> 8 | E8: =D8*$B$13 -> 16 | F8: =COUNTIF(Tareas!$F$2:$F$135,A8) -> 15 | G8: =COUNTIFS(Tareas!$F$2:$F$135,A8,Tareas!$P$2:$P$135,"Pendiente") -> 15 | H8: =COUNTIFS(Tareas!$F$2:$F$135,A8,Tareas!$P$2:$P$135,"En curso") -> 0 | I8: =COUNTIFS(Tareas!$F$2:$F$135,A8,Tareas!$P$2:$P$135,"Bloqueada") -> 0 | J8: =COUNTIFS(Tareas!$F$2:$F$135,A8,Tareas!$P$2:$P$135,"Hecha") -> 0 | K8: =IF(F8=0,0,J8/F8) -> 0
A9: Total | C9: =SUM(C2:C8) -> 30 | D9: =SUM(D2:D8) -> 86 | E9: =SUM(E2:E8) -> 172 | F9: =SUM(F2:F8) -> 134 | G9: =SUM(G2:G8) -> 134 | H9: =SUM(H2:H8) -> 0 | I9: =SUM(I2:I8) -> 0 | J9: =SUM(J2:J8) -> 0 | K9: =IF(F9=0,0,J9/F9) -> 0
A12: Supuestos (celdas en azul: editables)
A13: Horas por punto (referencia) | B13: 2 | C13: Referencia de encaje acordada en el backlog; el seguimiento del sprint es en puntos.
A14: Horas disponibles por persona en el sprint | B14: 18 | C14: 9 h/semana × 2 semanas (Documento de Proyecto). El equipo retiró el tope de 16 h de tarea.
A15: Capacidad nominal del equipo (h) | B15: =B14*COUNTA(A2:A8) -> 126
A16: Horas equivalentes comprometidas | B16: =E9 -> 172
A17: Diferencia (capacidad − compromiso) | B17: =B15-B16 -> -46
A18: En rojo, en la columna Horas equivalentes: personas por encima de sus horas disponibles.

Sheet Entregables S10
A1: Entregable de la Semana 10 | B1: Versión | C1: Historias | D1: Responsable principal | E1: Tarea que lo emite
A2: Presentación de la entrega (máx. 40 min) y buzón | B2: — | C2: HU-328, HU-329 | D2: Carlos | E2: T-329.4
A3: Despliegue de componentes en QA | B3: — | C3: HU-313, HU-314 | D3: Veli | E3: T-314.6
A4: Informe de pruebas | B4: — | C4: HU-315, HU-316 | D4: Tomás | E4: T-316.3
A5: Incremento de valor | B5: — | C5: HU-301 a HU-312, HU-330, HU-317 | D5: Sebastián, Damián | E5: T-314.6
A6: Documento de Requerimientos | B6: SRS V4 | C6: HU-324 | D6: Alex | E6: T-324.4
A7: Backlog | B7: Backlog V4 | C7: HU-327 | D7: Alex | E7: T-327.3
A8: Documento de Arquitectura | B8: SAD V3 | C8: HU-318, HU-319, HU-321 | D8: Sara | E8: T-321.2
A9: Documento de Diseño Detallado | B9: DD V3 | C9: HU-322 | D9: Alex | E9: T-322.5
A10: Documento de Infraestructura | B10: Infraestructura V2 | C10: HU-323 | D10: Veli | E10: T-323.4
A11: Documento de Diseño (vistas 4+1 y C4) | B11: SDD V2 | C11: HU-320 | D11: Sara | E11: T-320.6
A12: Documento de Pruebas | B12: TD V1 | C12: HU-325 | D12: Tomás | E12: T-325.6

Sheet Could
A1: ID | B1: Título | C1: Origen | D1: Pts | E1: Escenarios que habilita | F1: Depende de | G1: Nota
A2: C-01 | B2: Web: registro de donación, tamizaje, despacho y diálogo de desecho | C2: RF-03, RF-05, RF-06 | D2: 5 | E2: EC-19 y EC-41 completos, EC-28 | F2: T-317.3, T-306.3, T-308.2, T-310.2
A3: C-02 | B3: Servicio Institucional + db_institucional: jerarquía, instituciones y vista territorial del coordinador | C3: RF-09, RNF-02 | D3: 5 | E3: EC-01 con U5 | F3: T-305.1, T-303.1 | G3: Necesita un responsable .NET
A4: C-03 | B4: Creación y edición de campañas | C4: RF-08 | D4: 2 | E4: — | F4: C-02, T-312.2 | G4: Arista 10: Campañas pide la ruta territorial a Institucional
A5: C-04 | B5: Fraccionamiento de la donación en componentes | C5: RF-03 | D5: 3 | E5: — | F5: T-307.2
A6: C-05 | B6: Prometheus y Grafana en QA (entradas 31 y 32) | C6: Herramientas V3.0 | D6: 3 | E6: — | F6: T-314.2
A7: C-06 | B7: Alertas de escasez y de vencimiento próximo | C7: RF-19, RF-20 | D7: 3 | E7: — | F7: T-309.1, T-311.1
A8: C-07 | B8: Primera campaña de carga con Gatling sobre el inventario | C8: RNF-04 | D8: 5 | E8: — | F8: T-314.6, C-05
A9: C-08 | B9: Registro voluntario de donante (anónimo y con perfil) | C9: RF-01, RNF-03 | D9: 5 | E9: EC-17 | F9: T-306.1, T-330.3
